roastcoffea/__init__.py
roastcoffea/collector.py
roastcoffea/decorator.py
roastcoffea/instrumentation.py
roastcoffea/measurements.py
roastcoffea/reporter.py
roastcoffea/utils.py
roastcoffea/aggregation/__init__.py
roastcoffea/aggregation/branch_coverage.py
roastcoffea/aggregation/chunk.py
roastcoffea/aggregation/core.py
roastcoffea/aggregation/efficiency.py
roastcoffea/aggregation/fine_metrics.py
roastcoffea/aggregation/workflow.py
roastcoffea/aggregation/backends/__init__.py
roastcoffea/aggregation/backends/base.py
roastcoffea/aggregation/backends/dask.py
roastcoffea/backends/__init__.py
roastcoffea/backends/base.py
roastcoffea/backends/dask.py
roastcoffea/export/__init__.py
roastcoffea/export/measurements.py
roastcoffea/export/reporter.py
roastcoffea/export/tables.py
roastcoffea/visualization/__init__.py
roastcoffea/visualization/utils.py
roastcoffea/visualization/dashboards/__init__.py
roastcoffea/visualization/dashboards/main.py
roastcoffea/visualization/plots/__init__.py
roastcoffea/visualization/plots/chunks.py
roastcoffea/visualization/plots/cpu.py
roastcoffea/visualization/plots/io.py
roastcoffea/visualization/plots/memory.py
roastcoffea/visualization/plots/per_task.py
roastcoffea/visualization/plots/scaling.py
roastcoffea/visualization/plots/throughput.py
roastcoffea/visualization/plots/workers.py
roastcoffea-0.1.2.dist-info/METADATA
roastcoffea-0.1.2.dist-info/WHEEL
roastcoffea-0.1.2.dist-info/licenses/LICENSE
roastcoffea-0.1.2.dist-info/RECORD
