Metadata-Version: 2.4
Name: roastcoffea
Version: 0.1.2
Summary: Comprehensive performance monitoring and metrics collection for Coffea-based High Energy Physics analysis workflows
Project-URL: Homepage, https://github.com/MoAly98/roastcoffea
Project-URL: Bug Tracker, https://github.com/MoAly98/roastcoffea/issues
Project-URL: Discussions, https://github.com/MoAly98/roastcoffea/discussions
Project-URL: Changelog, https://github.com/MoAly98/roastcoffea/releases
Author-email: Mohamed Aly <mohamed.aly@cern.ch>
License-Expression: BSD-3-Clause
License-File: LICENSE
Classifier: Development Status :: 4 - Beta
Classifier: Intended Audience :: Developers
Classifier: Intended Audience :: Science/Research
Classifier: Operating System :: OS Independent
Classifier: Programming Language :: Python
Classifier: Programming Language :: Python :: 3
Classifier: Programming Language :: Python :: 3 :: Only
Classifier: Programming Language :: Python :: 3.11
Classifier: Programming Language :: Python :: 3.12
Classifier: Programming Language :: Python :: 3.13
Classifier: Topic :: Scientific/Engineering
Classifier: Typing :: Typed
Requires-Python: <3.14,>=3.12
Requires-Dist: awkward>=2.0.0
Requires-Dist: bokeh>=3.0.0
Requires-Dist: coffea>=2025.12.0
Requires-Dist: dask[distributed]>=2024.0.0
Requires-Dist: distributed>=2024.0.0
Requires-Dist: matplotlib>=3.5.0
Requires-Dist: mplcursors>=0.5.0
Requires-Dist: numpy>=1.20.0
Requires-Dist: psutil>=5.9.0
Requires-Dist: rich>=13.0.0
Requires-Dist: wadler-lindig<0.2,>=0.1.7
